fastapi_cached/__init__.py
fastapi_cached/cache.py
fastapi_cached/inspector.py
fastapi_cached-0.1.0.dist-info/METADATA
fastapi_cached-0.1.0.dist-info/WHEEL
fastapi_cached-0.1.0.dist-info/RECORD
