Metadata-Version: 2.3
Name: fastapi-cached
Version: 0.1.0
Summary: A simple package to pre-compute and cache FastAPI endpoints with discrete parameters.
Author: Jithin Sankar
Requires-Python: >=3.8,<4.0
Classifier: Programming Language :: Python :: 3
Classifier: Programming Language :: Python :: 3.8
Classifier: Programming Language :: Python :: 3.9
Classifier: Programming Language :: Python :: 3.10
Classifier: Programming Language :: Python :: 3.11
Classifier: Programming Language :: Python :: 3.12
Classifier: Programming Language :: Python :: 3.13
Requires-Dist: fastapi (>=0.104.1,<0.105.0)
